[{"conclusion":"success","headBranch":"main","headSha":"85987176bdd938fb6cbdf5fc817b12190348ec35","name":"C25 Pages","startedAt":"2026-02-26T01:45:32Z","status":"completed"},{"conclusion":"success","headBranch":"main","headSha":"85987176bdd938fb6cbdf5fc817b12190348ec35","name":"pages build and deployment","startedAt":"2026-02-26T01:45:32Z","status":"completed"},{"conclusion":"success","headBranch":"main","headSha":"85e68deb56a6a2552e7c4fa24ecf674bbb6883e5","name":"C25 Pages","startedAt":"2026-02-26T01:44:35Z","status":"completed"},{"conclusion":"success","headBranch":"main","headSha":"85e68deb56a6a2552e7c4fa24ecf674bbb6883e5","name":"pages build and deployment","startedAt":"2026-02-26T01:44:35Z","status":"completed"},{"conclusion":"success","headBranch":"main","headSha":"d4bba1668145a40f130754a2681c1d8c55bf2458","name":"C25 Pages","startedAt":"2026-02-26T01:42:03Z","status":"completed"},{"conclusion":"success","headBranch":"main","headSha":"d4bba1668145a40f130754a2681c1d8c55bf2458","name":"pages build and deployment","startedAt":"2026-02-26T01:42:02Z","status":"completed"},{"conclusion":"success","headBranch":"main","headSha":"86aa227e55c16ff7d8a406023dcdd1b4122f6994","name":"C25 Pages","startedAt":"2026-02-26T01:34:16Z","status":"completed"},{"conclusion":"success","headBranch":"main","headSha":"86aa227e55c16ff7d8a406023dcdd1b4122f6994","name":"pages build and deployment","startedAt":"2026-02-26T01:34:15Z","status":"completed"},{"conclusion":"success","headBranch":"main","headSha":"28f63c3841236655c991bb3287fb54d17d6fb02d","name":"C25 Pages","startedAt":"2026-02-26T01:29:07Z","status":"completed"},{"conclusion":"success","headBranch":"main","headSha":"28f63c3841236655c991bb3287fb54d17d6fb02d","name":"pages build and deployment","startedAt":"2026-02-26T01:29:07Z","status":"completed"},{"conclusion":"success","headBranch":"main","headSha":"0eb25be7c1d10d00a8aebe36be551564cbf65539","name":"C25 Pages","startedAt":"2026-02-26T01:28:05Z","status":"completed"},{"conclusion":"success","headBranch":"main","headSha":"0eb25be7c1d10d00a8aebe36be551564cbf65539","name":"pages build and deployment","startedAt":"2026-02-26T01:28:05Z","status":"completed"},{"conclusion":"success","headBranch":"main","headSha":"2452aa8b9c6eed4ee231da8db493272a03475149","name":"C25 Pages","startedAt":"2026-02-26T01:25:30Z","status":"completed"},{"conclusion":"success","headBranch":"main","headSha":"2452aa8b9c6eed4ee231da8db493272a03475149","name":"pages build and deployment","startedAt":"2026-02-26T01:25:29Z","status":"completed"},{"conclusion":"success","headBranch":"main","headSha":"ca210398905cfccbd837cce1d5838608f2562a9d","name":"C25 Pages","startedAt":"2026-02-26T01:13:03Z","status":"completed"},{"conclusion":"success","headBranch":"main","headSha":"ca210398905cfccbd837cce1d5838608f2562a9d","name":"pages build and deployment","startedAt":"2026-02-26T01:13:01Z","status":"completed"}]
